tsu4lape.py
tsu4lape-0.2.dist-info/DESCRIPTION.rst
tsu4lape-0.2.dist-info/METADATA
tsu4lape-0.2.dist-info/RECORD
tsu4lape-0.2.dist-info/WHEEL
tsu4lape-0.2.dist-info/metadata.json
tsu4lape-0.2.dist-info/top_level.txt
