Metadata-Version: 2.0
Name: tsu4lape
Version: 0.2
Summary: A simple test suite for lazy people
Home-page: https://github.com/Bstiler/Tsu4Lape
Author: Bstiler
Author-email: Bruno08new12@gmail.com
License: UNKNOWN
Keywords: test setuptools development
Platform: UNKNOWN
Requires-Dist: demjson
